cognito_pyauth/__init__.py
cognito_pyauth/auth.py
cognito_pyauth/config.py
cognito_pyauth/exceptions.py
cognito_pyauth/logger.py
cognito_pyauth/schemas.py
cognito_pyauth/utils.py
cognito_pyauth-1.3.5.dist-info/METADATA
cognito_pyauth-1.3.5.dist-info/WHEEL
cognito_pyauth-1.3.5.dist-info/RECORD
