Metadata-Version: 2.1
Name: cognito-pyauth
Version: 1.3.5
Summary: 
Author: fuuga
Requires-Python: >=3.8,<4.0
Classifier: Programming Language :: Python :: 3
Classifier: Programming Language :: Python :: 3.8
Classifier: Programming Language :: Python :: 3.9
Classifier: Programming Language :: Python :: 3.10
Classifier: Programming Language :: Python :: 3.11
Classifier: Programming Language :: Python :: 3.12
Requires-Dist: PyJWT[crypto] (>=2.0,<3.0)
Requires-Dist: boto3 (>=1.0,<2.0)
Requires-Dist: fastapi (>=0.75.0,<1.0)
Requires-Dist: pydantic (>=2.0,<3.0)
Requires-Dist: requests (>=2.0,<3.0)
